screencolor/__init__.py
screencolor/sc.py
screencolor-1.0.1.dist-info/LICENSE
screencolor-1.0.1.dist-info/METADATA
screencolor-1.0.1.dist-info/WHEEL
screencolor-1.0.1.dist-info/top_level.txt
screencolor-1.0.1.dist-info/RECORD
